moltbook/__init__.py
moltbook/_compat.py
moltbook/_http.py
moltbook/client.py
moltbook/config.py
moltbook/exceptions.py
moltbook/models/__init__.py
moltbook/models/agent.py
moltbook/models/comment.py
moltbook/models/common.py
moltbook/models/post.py
moltbook/models/submolt.py
moltbook/resources/__init__.py
moltbook/resources/agents.py
moltbook/resources/comments.py
moltbook/resources/feed.py
moltbook/resources/posts.py
moltbook/resources/search.py
moltbook/resources/submolts.py
moltbook_sdk-0.1.0.dist-info/METADATA
moltbook_sdk-0.1.0.dist-info/WHEEL
moltbook_sdk-0.1.0.dist-info/licenses/LICENSE
moltbook_sdk-0.1.0.dist-info/RECORD
